comic_text_detector/LICENSE
comic_text_detector/__init__.py
comic_text_detector/basemodel.py
comic_text_detector/db_dataset.py
comic_text_detector/inference.py
comic_text_detector/seg_dataset.py
comic_text_detector/text_rendering.py
comic_text_detector/train_db.py
comic_text_detector/train_seg.py
comic_text_detector/models/__init__.py
comic_text_detector/models/yolov5/__init__.py
comic_text_detector/models/yolov5/common.py
comic_text_detector/models/yolov5/yolo.py
comic_text_detector/utils/__init__.py
comic_text_detector/utils/db_utils.py
comic_text_detector/utils/export.py
comic_text_detector/utils/general.py
comic_text_detector/utils/imgproc_utils.py
comic_text_detector/utils/io_utils.py
comic_text_detector/utils/loss.py
comic_text_detector/utils/textblock.py
comic_text_detector/utils/textmask.py
comic_text_detector/utils/weight_init.py
comic_text_detector/utils/yolov5_utils.py
mokuro/__init__.py
mokuro/__main__.py
mokuro/_version.py
mokuro/cache.py
mokuro/env.py
mokuro/manga_page_ocr.py
mokuro/mokuro_generator.py
mokuro/run.py
mokuro/utils.py
mokuro/volume.py
mokuro/assets/panzoom.min.js
mokuro/assets/icons/chevron-left-double-svgrepo-com.svg
mokuro/assets/icons/chevron-left-svgrepo-com.svg
mokuro/assets/icons/chevron-right-double-svgrepo-com.svg
mokuro/assets/icons/chevron-right-svgrepo-com.svg
mokuro/assets/icons/cross-svgrepo-com.svg
mokuro/assets/icons/expand-svgrepo-com.svg
mokuro/assets/icons/expand-width-svgrepo-com.svg
mokuro/assets/icons/fullscreen-svgrepo-com.svg
mokuro/assets/icons/menu-hamburger-svgrepo-com.svg
mokuro/legacy/__init__.py
mokuro/legacy/overlay_generator.py
mokuro/legacy/script.js
mokuro/legacy/styles.css
mokuro-0.2.1.dist-info/LICENSE
mokuro-0.2.1.dist-info/METADATA
mokuro-0.2.1.dist-info/WHEEL
mokuro-0.2.1.dist-info/entry_points.txt
mokuro-0.2.1.dist-info/top_level.txt
mokuro-0.2.1.dist-info/RECORD
