Metadata-Version: 2.1
Name: mokuro
Version: 0.2.1
Summary: Browser reader for manga with selectable text
Author-email: Maciej Budyś <kha-white@mail.com>
License: GNU GENERAL PUBLIC LICENSE
Project-URL: Homepage, https://github.com/kha-white/mokuro
Classifier: Programming Language :: Python :: 3
Requires-Python: >=3.6
License-File: LICENSE
Requires-Dist: fire
Requires-Dist: loguru
Requires-Dist: manga-ocr >=0.1.7
Requires-Dist: natsort
Requires-Dist: numpy
Requires-Dist: opencv-python >=4.1.2
Requires-Dist: Pillow >=7.1.2
Requires-Dist: pyclipper
Requires-Dist: requests
Requires-Dist: scipy
Requires-Dist: setuptools
Requires-Dist: shapely
Requires-Dist: torch >=1.7.0
Requires-Dist: torchsummary
Requires-Dist: torchvision >=0.8.1
Requires-Dist: transformers >=4.25.0
Requires-Dist: tqdm >=4.41.0
Requires-Dist: yattag
Provides-Extra: dev
Requires-Dist: pytest ; extra == 'dev'
Requires-Dist: ruff ; extra == 'dev'
